pygments_rzk/__init__.py
pygments_rzk-0.1.4.dist-info/LICENSE
pygments_rzk-0.1.4.dist-info/METADATA
pygments_rzk-0.1.4.dist-info/WHEEL
pygments_rzk-0.1.4.dist-info/entry_points.txt
pygments_rzk-0.1.4.dist-info/top_level.txt
pygments_rzk-0.1.4.dist-info/RECORD
