Metadata-Version: 2.1
Name: pygments-rzk
Version: 0.1.4
Summary: Pygments lexer for Rzk language (of proof assistant for synthetic ∞-categories).
Home-page: https://github.com/rzk-lang/pygments-rzk
Author: Nikolai Kudasov
Author-email: nickolay.kudasov@gmail.com
License: BSD 3
Keywords: pygments rzk lexer
Classifier: Environment :: Plugins
Classifier: Operating System :: OS Independent
Classifier: Programming Language :: Python
Classifier: Programming Language :: Python :: 2
Classifier: Programming Language :: Python :: 3
Classifier: Topic :: Software Development :: Libraries :: Python Modules
License-File: LICENSE
Requires-Dist: pygments >=1.4
